metasearch/__init__.py
metasearch-5.1.dist-info/METADATA
metasearch-5.1.dist-info/WHEEL
metasearch-5.1.dist-info/entry_points.txt
metasearch-5.1.dist-info/top_level.txt
metasearch-5.1.dist-info/RECORD
