Metadata-Version: 2.1
Name: metasearch
Version: 5.1
Summary: Pre built metasearch repository for easy uses.
Home-page: https://github.com/dumb-stuff/Meta-search
Author: Rukchad Wongprayoon
Author-email: contact@biomooping.tk
License: MIT
Keywords: Tools
Platform: UNKNOWN
Requires-Dist: flask
Requires-Dist: requests
Requires-Dist: googlesearch-python
Requires-Dist: asgiref
